fee.py
fee-0.2.0.dist-info/entry_points.txt
fee-0.2.0.dist-info/LICENSE
fee-0.2.0.dist-info/WHEEL
fee-0.2.0.dist-info/METADATA
fee-0.2.0.dist-info/RECORD
